j2ipaddr/__init__.py
j2ipaddr/filters.py
j2ipaddr-1.0.6.dist-info/LICENSE
j2ipaddr-1.0.6.dist-info/METADATA
j2ipaddr-1.0.6.dist-info/WHEEL
j2ipaddr-1.0.6.dist-info/top_level.txt
j2ipaddr-1.0.6.dist-info/RECORD
