Metadata-Version: 2.1
Name: j2ipaddr
Version: 1.0.6
Summary: Jinja2 filters for IP addresses, the easy way
Author-email: Arturo Baldo <baldoarturo@mail.com>
Project-URL: Homepage, https://github.com/baldoarturo/j2ipaddr
Keywords: jinja2,jinja,filters,netaddr,ipaddr,networking
Classifier: License :: OSI Approved :: GNU General Public License v3 or later (GPLv3+)
Classifier: Programming Language :: Python
Classifier: Programming Language :: Python :: 3
Requires-Python: >=3.8
License-File: LICENSE
Requires-Dist: netaddr
